[
  {
    "verse_key": "56:1",
    "timestamp_from": 4220,
    "timestamp_to": 8590,
    "duration": 4370,
    "segments": [
      [
        1,
        4520,
        5420
      ],
      [
        2,
        5420,
        6570
      ],
      [
        3,
        6650,
        8590
      ]
    ]
  },
  {
    "verse_key": "56:2",
    "timestamp_from": 8690,
    "timestamp_to": 13040,
    "duration": 4350,
    "segments": [
      [
        1,
        8890,
        9890
      ],
      [
        2,
        9890,
        11270
      ],
      [
        3,
        11270,
        13040
      ]
    ]
  },
  {
    "verse_key": "56:3",
    "timestamp_from": 13090,
    "timestamp_to": 15840,
    "duration": 2750,
    "segments": [
      [
        1,
        13090,
        14500
      ],
      [
        2,
        14540,
        15840
      ]
    ]
  },
  {
    "verse_key": "56:4",
    "timestamp_from": 16320,
    "timestamp_to": 20840,
    "duration": 4520,
    "segments": [
      [
        1,
        16520,
        17320
      ],
      [
        2,
        17320,
        18470
      ],
      [
        3,
        18470,
        19160
      ],
      [
        4,
        19160,
        20840
      ]
    ]
  },
  {
    "verse_key": "56:5",
    "timestamp_from": 21020,
    "timestamp_to": 24790,
    "duration": 3770,
    "segments": [
      [
        1,
        21020,
        22200
      ],
      [
        2,
        22220,
        23400
      ],
      [
        3,
        23400,
        24790
      ]
    ]
  },
  {
    "verse_key": "56:6",
    "timestamp_from": 25050,
    "timestamp_to": 32350,
    "duration": 7300,
    "segments": [
      [
        1,
        25250,
        26250
      ],
      [
        2,
        26250,
        30360
      ],
      [
        3,
        30360,
        32350
      ]
    ]
  },
  {
    "verse_key": "56:7",
    "timestamp_from": 32730,
    "timestamp_to": 38060,
    "duration": 5330,
    "segments": [
      [
        1,
        33030,
        34790
      ],
      [
        2,
        34790,
        36800
      ],
      [
        3,
        36800,
        38060
      ]
    ]
  },
  {
    "verse_key": "56:8",
    "timestamp_from": 38260,
    "timestamp_to": 44010,
    "duration": 5750,
    "segments": [
      [
        1,
        38460,
        39860
      ],
      [
        2,
        39880,
        41140
      ],
      [
        3,
        41140,
        41580
      ],
      [
        4,
        41580,
        42680
      ],
      [
        5,
        42740,
        44010
      ]
    ]
  },
  {
    "verse_key": "56:9",
    "timestamp_from": 44310,
    "timestamp_to": 50110,
    "duration": 5800,
    "segments": [
      [
        1,
        44510,
        45910
      ],
      [
        2,
        45950,
        47310
      ],
      [
        3,
        47310,
        47720
      ],
      [
        4,
        47720,
        48850
      ],
      [
        5,
        48890,
        50110
      ]
    ]
  },
  {
    "verse_key": "56:10",
    "timestamp_from": 50230,
    "timestamp_to": 54400,
    "duration": 4170,
    "segments": [
      [
        1,
        50430,
        52160
      ],
      [
        2,
        52160,
        54400
      ]
    ]
  },
  {
    "verse_key": "56:11",
    "timestamp_from": 54600,
    "timestamp_to": 59960,
    "duration": 5360,
    "segments": [
      [
        1,
        54600,
        57100
      ],
      [
        2,
        57260,
        59960
      ]
    ]
  },
  {
    "verse_key": "56:12",
    "timestamp_from": 60080,
    "timestamp_to": 63810,
    "duration": 3730,
    "segments": [
      [
        1,
        59980,
        60440
      ],
      [
        2,
        60440,
        62010
      ],
      [
        3,
        62350,
        63810
      ]
    ]
  },
  {
    "verse_key": "56:13",
    "timestamp_from": 63990,
    "timestamp_to": 68030,
    "duration": 4040,
    "segments": [
      [
        1,
        64190,
        65650
      ],
      [
        2,
        65650,
        66110
      ],
      [
        3,
        66150,
        68030
      ]
    ]
  },
  {
    "verse_key": "56:14",
    "timestamp_from": 68130,
    "timestamp_to": 72660,
    "duration": 4530,
    "segments": [
      [
        1,
        68330,
        69960
      ],
      [
        2,
        69960,
        70410
      ],
      [
        3,
        70430,
        72660
      ]
    ]
  },
  {
    "verse_key": "56:15",
    "timestamp_from": 72940,
    "timestamp_to": 76180,
    "duration": 3240,
    "segments": [
      [
        1,
        72940,
        73630
      ],
      [
        2,
        73630,
        74850
      ],
      [
        3,
        74850,
        76180
      ]
    ]
  },
  {
    "verse_key": "56:16",
    "timestamp_from": 76320,
    "timestamp_to": 81310,
    "duration": 4990,
    "segments": [
      [
        1,
        76520,
        78140
      ],
      [
        2,
        78140,
        79230
      ],
      [
        3,
        79230,
        81310
      ]
    ]
  },
  {
    "verse_key": "56:17",
    "timestamp_from": 81490,
    "timestamp_to": 87350,
    "duration": 5860,
    "segments": [
      [
        1,
        81490,
        82350
      ],
      [
        2,
        82350,
        83410
      ],
      [
        3,
        83410,
        85070
      ],
      [
        4,
        85070,
        87350
      ]
    ]
  },
  {
    "verse_key": "56:18",
    "timestamp_from": 87650,
    "timestamp_to": 94580,
    "duration": 6930,
    "segments": [
      [
        1,
        87650,
        89440
      ],
      [
        2,
        89440,
        90990
      ],
      [
        3,
        90990,
        92680
      ],
      [
        4,
        92680,
        93250
      ],
      [
        5,
        93250,
        94580
      ]
    ]
  },
  {
    "verse_key": "56:19",
    "timestamp_from": 94600,
    "timestamp_to": 100990,
    "duration": 6390,
    "segments": [
      [
        1,
        94800,
        95410
      ],
      [
        2,
        95410,
        97060
      ],
      [
        3,
        97060,
        98040
      ],
      [
        4,
        98040,
        98680
      ],
      [
        5,
        98680,
        100990
      ]
    ]
  },
  {
    "verse_key": "56:20",
    "timestamp_from": 101010,
    "timestamp_to": 107010,
    "duration": 6000,
    "segments": [
      [
        1,
        101210,
        103090
      ],
      [
        2,
        103090,
        104320
      ],
      [
        3,
        104320,
        107010
      ]
    ]
  },
  {
    "verse_key": "56:21",
    "timestamp_from": 107210,
    "timestamp_to": 113460,
    "duration": 6250,
    "segments": [
      [
        1,
        107410,
        108260
      ],
      [
        2,
        108260,
        109595
      ],
      [
        3,
        109595,
        110950
      ],
      [
        4,
        110950,
        113460
      ]
    ]
  },
  {
    "verse_key": "56:22",
    "timestamp_from": 113660,
    "timestamp_to": 116460,
    "duration": 2800,
    "segments": [
      [
        1,
        113860,
        115140
      ],
      [
        2,
        115140,
        116460
      ]
    ]
  },
  {
    "verse_key": "56:23",
    "timestamp_from": 116760,
    "timestamp_to": 122110,
    "duration": 5350,
    "segments": [
      [
        1,
        116760,
        118280
      ],
      [
        2,
        118360,
        119090
      ],
      [
        3,
        119090,
        122110
      ]
    ]
  },
  {
    "verse_key": "56:24",
    "timestamp_from": 122250,
    "timestamp_to": 128890,
    "duration": 6640,
    "segments": [
      [
        1,
        122450,
        125830
      ],
      [
        2,
        125830,
        126570
      ],
      [
        3,
        126590,
        127550
      ],
      [
        4,
        127550,
        128890
      ]
    ]
  },
  {
    "verse_key": "56:25",
    "timestamp_from": 129080,
    "timestamp_to": 135880,
    "duration": 6800,
    "segments": [
      [
        1,
        129280,
        129740
      ],
      [
        2,
        129740,
        131170
      ],
      [
        3,
        131170,
        132070
      ],
      [
        4,
        132070,
        133830
      ],
      [
        5,
        133830,
        134470
      ],
      [
        6,
        134470,
        135880
      ]
    ]
  },
  {
    "verse_key": "56:26",
    "timestamp_from": 136160,
    "timestamp_to": 142930,
    "duration": 6770,
    "segments": [
      [
        1,
        136360,
        137160
      ],
      [
        2,
        137220,
        138890
      ],
      [
        3,
        138910,
        141340
      ],
      [
        4,
        141340,
        142930
      ]
    ]
  },
  {
    "verse_key": "56:27",
    "timestamp_from": 142990,
    "timestamp_to": 149640,
    "duration": 6650,
    "segments": [
      [
        1,
        143190,
        144590
      ],
      [
        2,
        144590,
        145770
      ],
      [
        3,
        145770,
        146360
      ],
      [
        4,
        146360,
        147630
      ],
      [
        5,
        147690,
        149640
      ]
    ]
  },
  {
    "verse_key": "56:28",
    "timestamp_from": 150060,
    "timestamp_to": 153760,
    "duration": 3700,
    "segments": [
      [
        1,
        150260,
        150840
      ],
      [
        2,
        150860,
        152500
      ],
      [
        3,
        152500,
        153760
      ]
    ]
  },
  {
    "verse_key": "56:29",
    "timestamp_from": 154160,
    "timestamp_to": 157480,
    "duration": 3320,
    "segments": [
      [
        1,
        154360,
        155830
      ],
      [
        2,
        155830,
        157480
      ]
    ]
  },
  {
    "verse_key": "56:30",
    "timestamp_from": 157930,
    "timestamp_to": 162090,
    "duration": 4160,
    "segments": [
      [
        1,
        158130,
        160190
      ],
      [
        2,
        160190,
        162090
      ]
    ]
  },
  {
    "verse_key": "56:31",
    "timestamp_from": 162470,
    "timestamp_to": 169300,
    "duration": 6830,
    "segments": [
      [
        1,
        162770,
        166300
      ],
      [
        2,
        166300,
        169300
      ]
    ]
  },
  {
    "verse_key": "56:32",
    "timestamp_from": 169720,
    "timestamp_to": 173620,
    "duration": 3900,
    "segments": [
      [
        1,
        169920,
        172320
      ],
      [
        2,
        172340,
        173620
      ]
    ]
  },
  {
    "verse_key": "56:33",
    "timestamp_from": 173920,
    "timestamp_to": 179370,
    "duration": 5450,
    "segments": [
      [
        1,
        173920,
        174440
      ],
      [
        2,
        174440,
        177120
      ],
      [
        3,
        177120,
        177790
      ],
      [
        4,
        177790,
        179370
      ]
    ]
  },
  {
    "verse_key": "56:34",
    "timestamp_from": 179590,
    "timestamp_to": 183390,
    "duration": 3800,
    "segments": [
      [
        1,
        179590,
        181900
      ],
      [
        2,
        181900,
        183390
      ]
    ]
  },
  {
    "verse_key": "56:35",
    "timestamp_from": 183410,
    "timestamp_to": 191600,
    "duration": 8190,
    "segments": [
      [
        1,
        183610,
        184810
      ],
      [
        2,
        184810,
        187910
      ],
      [
        3,
        187910,
        191600
      ]
    ]
  },
  {
    "verse_key": "56:36",
    "timestamp_from": 191900,
    "timestamp_to": 196640,
    "duration": 4740,
    "segments": [
      [
        1,
        191900,
        194490
      ],
      [
        2,
        194490,
        196640
      ]
    ]
  },
  {
    "verse_key": "56:37",
    "timestamp_from": 196710,
    "timestamp_to": 199130,
    "duration": 2420,
    "segments": [
      [
        1,
        196710,
        197690
      ],
      [
        2,
        197690,
        199130
      ]
    ]
  },
  {
    "verse_key": "56:38",
    "timestamp_from": 199410,
    "timestamp_to": 202450,
    "duration": 3040,
    "segments": [
      [
        1,
        199610,
        200930
      ],
      [
        2,
        200950,
        202450
      ]
    ]
  },
  {
    "verse_key": "56:39",
    "timestamp_from": 202590,
    "timestamp_to": 206840,
    "duration": 4250,
    "segments": [
      [
        1,
        202790,
        204420
      ],
      [
        2,
        204420,
        204890
      ],
      [
        3,
        204940,
        206840
      ]
    ]
  },
  {
    "verse_key": "56:40",
    "timestamp_from": 206900,
    "timestamp_to": 211960,
    "duration": 5060,
    "segments": [
      [
        1,
        207100,
        209770
      ],
      [
        2,
        209770,
        210200
      ],
      [
        3,
        210260,
        211960
      ]
    ]
  },
  {
    "verse_key": "56:41",
    "timestamp_from": 212140,
    "timestamp_to": 218450,
    "duration": 6310,
    "segments": [
      [
        1,
        212340,
        213720
      ],
      [
        2,
        213720,
        214960
      ],
      [
        3,
        214960,
        215410
      ],
      [
        4,
        215410,
        216530
      ],
      [
        5,
        216530,
        218450
      ]
    ]
  },
  {
    "verse_key": "56:42",
    "timestamp_from": 218570,
    "timestamp_to": 223920,
    "duration": 5350,
    "segments": [
      [
        1,
        218770,
        219290
      ],
      [
        2,
        219290,
        221640
      ],
      [
        3,
        221640,
        223920
      ]
    ]
  },
  {
    "verse_key": "56:43",
    "timestamp_from": 223990,
    "timestamp_to": 228740,
    "duration": 4750,
    "segments": [
      [
        1,
        223990,
        226090
      ],
      [
        2,
        226090,
        227030
      ],
      [
        3,
        227030,
        228540
      ]
    ]
  },
  {
    "verse_key": "56:44",
    "timestamp_from": 228840,
    "timestamp_to": 234170,
    "duration": 5330,
    "segments": [
      [
        1,
        229040,
        229720
      ],
      [
        2,
        229720,
        231940
      ],
      [
        3,
        231940,
        232700
      ],
      [
        4,
        232720,
        234170
      ]
    ]
  },
  {
    "verse_key": "56:45",
    "timestamp_from": 234330,
    "timestamp_to": 240230,
    "duration": 5900,
    "segments": [
      [
        1,
        234330,
        235700
      ],
      [
        2,
        235700,
        236770
      ],
      [
        3,
        236790,
        237530
      ],
      [
        4,
        237530,
        238450
      ],
      [
        5,
        238470,
        240190
      ]
    ]
  },
  {
    "verse_key": "56:46",
    "timestamp_from": 240470,
    "timestamp_to": 246120,
    "duration": 5650,
    "segments": [
      [
        1,
        240470,
        241570
      ],
      [
        2,
        241570,
        242910
      ],
      [
        3,
        242910,
        243400
      ],
      [
        4,
        243400,
        244880
      ],
      [
        5,
        244880,
        246120
      ]
    ]
  },
  {
    "verse_key": "56:47",
    "timestamp_from": 246260,
    "timestamp_to": 258050,
    "duration": 11790,
    "segments": [
      [
        1,
        246460,
        247580
      ],
      [
        2,
        247580,
        248980
      ],
      [
        3,
        248980,
        250000
      ],
      [
        4,
        250000,
        250840
      ],
      [
        5,
        250840,
        252090
      ],
      [
        6,
        252090,
        253070
      ],
      [
        7,
        253370,
        254740
      ],
      [
        8,
        254740,
        256130
      ],
      [
        9,
        256130,
        258050
      ]
    ]
  },
  {
    "verse_key": "56:48",
    "timestamp_from": 258190,
    "timestamp_to": 264460,
    "duration": 6270,
    "segments": [
      [
        1,
        258390,
        262540
      ],
      [
        2,
        262560,
        264360
      ]
    ]
  },
  {
    "verse_key": "56:49",
    "timestamp_from": 264600,
    "timestamp_to": 269110,
    "duration": 4510,
    "segments": [
      [
        1,
        264600,
        265050
      ],
      [
        2,
        265050,
        265920
      ],
      [
        3,
        265980,
        267420
      ],
      [
        4,
        267420,
        269110
      ]
    ]
  },
  {
    "verse_key": "56:50",
    "timestamp_from": 269160,
    "timestamp_to": 274750,
    "duration": 5590,
    "segments": [
      [
        1,
        269160,
        270870
      ],
      [
        2,
        270870,
        271510
      ],
      [
        3,
        271510,
        272600
      ],
      [
        4,
        272600,
        273680
      ],
      [
        5,
        273680,
        274750
      ]
    ]
  },
  {
    "verse_key": "56:51",
    "timestamp_from": 275050,
    "timestamp_to": 287080,
    "duration": 12030,
    "segments": [
      [
        1,
        275250,
        276620
      ],
      [
        2,
        276620,
        278070
      ],
      [
        3,
        278070,
        278810
      ],
      [
        4,
        278850,
        285240
      ],
      [
        5,
        285240,
        287080
      ]
    ]
  },
  {
    "verse_key": "56:52",
    "timestamp_from": 287360,
    "timestamp_to": 293550,
    "duration": 6190,
    "segments": [
      [
        1,
        287560,
        289270
      ],
      [
        2,
        289270,
        290240
      ],
      [
        3,
        290240,
        291520
      ],
      [
        4,
        291520,
        292240
      ],
      [
        5,
        292240,
        293550
      ]
    ]
  },
  {
    "verse_key": "56:53",
    "timestamp_from": 293630,
    "timestamp_to": 297350,
    "duration": 3720,
    "segments": [
      [
        1,
        293830,
        295480
      ],
      [
        2,
        295480,
        296130
      ],
      [
        3,
        296210,
        297350
      ]
    ]
  },
  {
    "verse_key": "56:54",
    "timestamp_from": 297510,
    "timestamp_to": 301880,
    "duration": 4370,
    "segments": [
      [
        1,
        297510,
        299170
      ],
      [
        2,
        299170,
        300040
      ],
      [
        3,
        300040,
        300470
      ],
      [
        4,
        300470,
        301880
      ]
    ]
  },
  {
    "verse_key": "56:55",
    "timestamp_from": 301940,
    "timestamp_to": 306100,
    "duration": 4160,
    "segments": [
      [
        1,
        302140,
        303960
      ],
      [
        2,
        303960,
        304700
      ],
      [
        3,
        304740,
        306100
      ]
    ]
  },
  {
    "verse_key": "56:56",
    "timestamp_from": 306440,
    "timestamp_to": 313170,
    "duration": 6730,
    "segments": [
      [
        1,
        306640,
        307900
      ],
      [
        2,
        307900,
        309370
      ],
      [
        3,
        309370,
        310310
      ],
      [
        4,
        310310,
        313170
      ]
    ]
  },
  {
    "verse_key": "56:57",
    "timestamp_from": 313610,
    "timestamp_to": 320200,
    "duration": 6590,
    "segments": [
      [
        1,
        313910,
        314560
      ],
      [
        2,
        314560,
        316230
      ],
      [
        3,
        316230,
        317380
      ],
      [
        4,
        317380,
        320000
      ]
    ]
  },
  {
    "verse_key": "56:58",
    "timestamp_from": 320440,
    "timestamp_to": 325300,
    "duration": 4860,
    "segments": [
      [
        1,
        320640,
        322710
      ],
      [
        2,
        322710,
        323160
      ],
      [
        3,
        323180,
        325300
      ]
    ]
  },
  {
    "verse_key": "56:59",
    "timestamp_from": 325560,
    "timestamp_to": 332910,
    "duration": 7350,
    "segments": [
      [
        1,
        325760,
        327250
      ],
      [
        2,
        327250,
        329140
      ],
      [
        3,
        329140,
        329580
      ],
      [
        4,
        329580,
        330270
      ],
      [
        5,
        330290,
        332910
      ]
    ]
  },
  {
    "verse_key": "56:60",
    "timestamp_from": 333230,
    "timestamp_to": 340290,
    "duration": 7060,
    "segments": [
      [
        1,
        333430,
        334090
      ],
      [
        2,
        334110,
        335510
      ],
      [
        3,
        335510,
        336630
      ],
      [
        4,
        336690,
        337470
      ],
      [
        5,
        337470,
        338100
      ],
      [
        6,
        338100,
        338730
      ],
      [
        7,
        338730,
        340290
      ]
    ]
  },
  {
    "verse_key": "56:61",
    "timestamp_from": 340360,
    "timestamp_to": 359100,
    "duration": 18740,
    "segments": [
      [
        1,
        340360,
        341030
      ],
      [
        2,
        341030,
        341780
      ],
      [
        3,
        341780,
        342850
      ],
      [
        4,
        342850,
        352620
      ],
      [
        5,
        352620,
        355530
      ],
      [
        6,
        355530,
        356060
      ],
      [
        7,
        356060,
        356520
      ],
      [
        8,
        356520,
        356960
      ],
      [
        9,
        356960,
        359100
      ]
    ]
  },
  {
    "verse_key": "56:62",
    "timestamp_from": 359580,
    "timestamp_to": 368530,
    "duration": 8950,
    "segments": [
      [
        1,
        359780,
        360680
      ],
      [
        2,
        360680,
        361820
      ],
      [
        3,
        362740,
        363780
      ],
      [
        4,
        363860,
        364950
      ],
      [
        5,
        364950,
        366100
      ],
      [
        6,
        366100,
        368530
      ]
    ]
  },
  {
    "verse_key": "56:63",
    "timestamp_from": 368810,
    "timestamp_to": 375130,
    "duration": 6320,
    "segments": [
      [
        1,
        369010,
        371370
      ],
      [
        2,
        371370,
        371810
      ],
      [
        3,
        371810,
        375130
      ]
    ]
  },
  {
    "verse_key": "56:64",
    "timestamp_from": 375350,
    "timestamp_to": 383140,
    "duration": 7790,
    "segments": [
      [
        1,
        375350,
        378110
      ],
      [
        2,
        378110,
        379620
      ],
      [
        3,
        379940,
        380410
      ],
      [
        4,
        380410,
        381050
      ],
      [
        5,
        381050,
        383140
      ]
    ]
  },
  {
    "verse_key": "56:65",
    "timestamp_from": 383300,
    "timestamp_to": 393550,
    "duration": 10250,
    "segments": [
      [
        1,
        383500,
        383930
      ],
      [
        2,
        383930,
        387120
      ],
      [
        3,
        387120,
        388660
      ],
      [
        4,
        388660,
        390080
      ],
      [
        5,
        390080,
        391280
      ],
      [
        6,
        391280,
        393550
      ]
    ]
  },
  {
    "verse_key": "56:66",
    "timestamp_from": 393930,
    "timestamp_to": 397960,
    "duration": 4030,
    "segments": [
      [
        1,
        394130,
        396010
      ],
      [
        2,
        396010,
        397960
      ]
    ]
  },
  {
    "verse_key": "56:67",
    "timestamp_from": 398260,
    "timestamp_to": 401660,
    "duration": 3400,
    "segments": [
      [
        1,
        398460,
        398940
      ],
      [
        2,
        398940,
        399670
      ],
      [
        3,
        399670,
        401660
      ]
    ]
  },
  {
    "verse_key": "56:68",
    "timestamp_from": 401880,
    "timestamp_to": 409350,
    "duration": 7470,
    "segments": [
      [
        1,
        402080,
        403860
      ],
      [
        2,
        403940,
        407150
      ],
      [
        3,
        407250,
        408060
      ],
      [
        4,
        408060,
        409350
      ]
    ]
  },
  {
    "verse_key": "56:69",
    "timestamp_from": 410050,
    "timestamp_to": 420300,
    "duration": 10250,
    "segments": [
      [
        1,
        410350,
        412320
      ],
      [
        2,
        412320,
        415090
      ],
      [
        3,
        415090,
        415580
      ],
      [
        4,
        415600,
        416400
      ],
      [
        5,
        416400,
        416850
      ],
      [
        6,
        416850,
        417540
      ],
      [
        7,
        417580,
        420300
      ]
    ]
  },
  {
    "verse_key": "56:70",
    "timestamp_from": 420680,
    "timestamp_to": 431010,
    "duration": 10330,
    "segments": [
      [
        1,
        420880,
        421310
      ],
      [
        2,
        421310,
        424450
      ],
      [
        3,
        424450,
        425860
      ],
      [
        4,
        425860,
        427670
      ],
      [
        5,
        427670,
        428990
      ],
      [
        6,
        428990,
        431010
      ]
    ]
  },
  {
    "verse_key": "56:71",
    "timestamp_from": 431510,
    "timestamp_to": 438580,
    "duration": 7070,
    "segments": [
      [
        1,
        431710,
        433470
      ],
      [
        2,
        435080,
        435920
      ],
      [
        3,
        436060,
        437010
      ],
      [
        4,
        437010,
        438580
      ]
    ]
  },
  {
    "verse_key": "56:72",
    "timestamp_from": 438980,
    "timestamp_to": 448870,
    "duration": 9890,
    "segments": [
      [
        1,
        439180,
        442290
      ],
      [
        2,
        442290,
        444190
      ],
      [
        3,
        444210,
        445760
      ],
      [
        4,
        445760,
        446200
      ],
      [
        5,
        446200,
        446890
      ],
      [
        6,
        446970,
        448870
      ]
    ]
  },
  {
    "verse_key": "56:73",
    "timestamp_from": 449370,
    "timestamp_to": 458280,
    "duration": 8910,
    "segments": [
      [
        1,
        449570,
        450270
      ],
      [
        2,
        450270,
        452210
      ],
      [
        3,
        452210,
        454660
      ],
      [
        4,
        454660,
        456000
      ],
      [
        5,
        456160,
        458280
      ]
    ]
  },
  {
    "verse_key": "56:74",
    "timestamp_from": 458760,
    "timestamp_to": 464470,
    "duration": 5710,
    "segments": [
      [
        1,
        459060,
        460480
      ],
      [
        2,
        460480,
        461310
      ],
      [
        3,
        461310,
        462200
      ],
      [
        4,
        462450,
        464470
      ]
    ]
  },
  {
    "verse_key": "56:75",
    "timestamp_from": 464490,
    "timestamp_to": 469430,
    "duration": 4940,
    "segments": [
      [
        1,
        464690,
        465360
      ],
      [
        2,
        465360,
        466330
      ],
      [
        3,
        466330,
        467770
      ],
      [
        4,
        468290,
        469430
      ]
    ]
  },
  {
    "verse_key": "56:76",
    "timestamp_from": 469610,
    "timestamp_to": 474880,
    "duration": 5270,
    "segments": [
      [
        1,
        469610,
        470920
      ],
      [
        2,
        470920,
        471910
      ],
      [
        3,
        472060,
        472540
      ],
      [
        4,
        472540,
        473870
      ],
      [
        5,
        473870,
        474880
      ]
    ]
  },
  {
    "verse_key": "56:77",
    "timestamp_from": 474920,
    "timestamp_to": 480340,
    "duration": 5420,
    "segments": [
      [
        1,
        475120,
        476430
      ],
      [
        2,
        476430,
        478440
      ],
      [
        3,
        478440,
        480340
      ]
    ]
  },
  {
    "verse_key": "56:78",
    "timestamp_from": 480600,
    "timestamp_to": 484110,
    "duration": 3510,
    "segments": [
      [
        1,
        480600,
        480900
      ],
      [
        2,
        480920,
        482870
      ],
      [
        3,
        482870,
        484110
      ]
    ]
  },
  {
    "verse_key": "56:79",
    "timestamp_from": 484370,
    "timestamp_to": 488610,
    "duration": 4240,
    "segments": [
      [
        1,
        484370,
        484610
      ],
      [
        2,
        484750,
        486190
      ],
      [
        3,
        486190,
        486830
      ],
      [
        4,
        486870,
        488610
      ]
    ]
  },
  {
    "verse_key": "56:80",
    "timestamp_from": 488870,
    "timestamp_to": 493720,
    "duration": 4850,
    "segments": [
      [
        1,
        488870,
        491085
      ],
      [
        2,
        491085,
        491380
      ],
      [
        3,
        491460,
        492200
      ],
      [
        4,
        492240,
        493720
      ]
    ]
  },
  {
    "verse_key": "56:81",
    "timestamp_from": 493980,
    "timestamp_to": 499400,
    "duration": 5420,
    "segments": [
      [
        1,
        493980,
        495290
      ],
      [
        2,
        495290,
        496370
      ],
      [
        3,
        496370,
        497960
      ],
      [
        4,
        497960,
        499400
      ]
    ]
  },
  {
    "verse_key": "56:82",
    "timestamp_from": 499460,
    "timestamp_to": 505930,
    "duration": 6470,
    "segments": [
      [
        1,
        499660,
        501130
      ],
      [
        2,
        501130,
        502260
      ],
      [
        3,
        502260,
        503850
      ],
      [
        4,
        503850,
        505930
      ]
    ]
  },
  {
    "verse_key": "56:83",
    "timestamp_from": 505990,
    "timestamp_to": 510540,
    "duration": 4550,
    "segments": [
      [
        1,
        506190,
        507230
      ],
      [
        2,
        507230,
        508010
      ],
      [
        3,
        508010,
        509170
      ],
      [
        4,
        509170,
        510540
      ]
    ]
  },
  {
    "verse_key": "56:84",
    "timestamp_from": 510620,
    "timestamp_to": 517680,
    "duration": 7060,
    "segments": [
      [
        1,
        510820,
        512700
      ],
      [
        2,
        512720,
        514760
      ],
      [
        3,
        514760,
        517680
      ]
    ]
  },
  {
    "verse_key": "56:85",
    "timestamp_from": 517720,
    "timestamp_to": 525210,
    "duration": 7490,
    "segments": [
      [
        1,
        517920,
        518730
      ],
      [
        2,
        518730,
        519650
      ],
      [
        3,
        519650,
        520540
      ],
      [
        4,
        520540,
        521620
      ],
      [
        5,
        521620,
        522700
      ],
      [
        6,
        522700,
        523110
      ],
      [
        7,
        523110,
        525110
      ]
    ]
  },
  {
    "verse_key": "56:86",
    "timestamp_from": 525510,
    "timestamp_to": 531260,
    "duration": 5750,
    "segments": [
      [
        1,
        525510,
        526550
      ],
      [
        2,
        526550,
        527390
      ],
      [
        3,
        527410,
        529010
      ],
      [
        4,
        529010,
        529770
      ],
      [
        5,
        529770,
        531260
      ]
    ]
  },
  {
    "verse_key": "56:87",
    "timestamp_from": 531520,
    "timestamp_to": 537520,
    "duration": 6000,
    "segments": [
      [
        1,
        531520,
        533290
      ],
      [
        2,
        533290,
        534120
      ],
      [
        3,
        534120,
        535900
      ],
      [
        4,
        535900,
        537520
      ]
    ]
  },
  {
    "verse_key": "56:88",
    "timestamp_from": 537820,
    "timestamp_to": 543450,
    "duration": 5630,
    "segments": [
      [
        1,
        537820,
        539210
      ],
      [
        2,
        539210,
        540310
      ],
      [
        3,
        540330,
        541060
      ],
      [
        4,
        541060,
        541530
      ],
      [
        5,
        541550,
        543450
      ]
    ]
  },
  {
    "verse_key": "56:89",
    "timestamp_from": 543670,
    "timestamp_to": 550760,
    "duration": 7090,
    "segments": [
      [
        1,
        543870,
        545620
      ],
      [
        2,
        545620,
        547880
      ],
      [
        3,
        547880,
        549770
      ],
      [
        4,
        549770,
        550760
      ]
    ]
  },
  {
    "verse_key": "56:90",
    "timestamp_from": 551000,
    "timestamp_to": 557550,
    "duration": 6550,
    "segments": [
      [
        1,
        551200,
        552530
      ],
      [
        2,
        552530,
        553320
      ],
      [
        3,
        553320,
        554070
      ],
      [
        4,
        554070,
        554440
      ],
      [
        5,
        554440,
        555630
      ],
      [
        6,
        555630,
        557550
      ]
    ]
  },
  {
    "verse_key": "56:91",
    "timestamp_from": 557700,
    "timestamp_to": 562230,
    "duration": 4530,
    "segments": [
      [
        1,
        557700,
        558950
      ],
      [
        2,
        559070,
        559450
      ],
      [
        3,
        559550,
        559650
      ],
      [
        4,
        559970,
        561150
      ],
      [
        5,
        561150,
        562230
      ]
    ]
  },
  {
    "verse_key": "56:92",
    "timestamp_from": 562490,
    "timestamp_to": 573820,
    "duration": 11330,
    "segments": [
      [
        1,
        562490,
        564050
      ],
      [
        2,
        564050,
        564990
      ],
      [
        3,
        564990,
        565690
      ],
      [
        4,
        565690,
        566130
      ],
      [
        5,
        566170,
        567860
      ],
      [
        6,
        567860,
        573820
      ]
    ]
  },
  {
    "verse_key": "56:93",
    "timestamp_from": 574140,
    "timestamp_to": 577990,
    "duration": 3850,
    "segments": [
      [
        1,
        574340,
        576310
      ],
      [
        2,
        576310,
        576700
      ],
      [
        3,
        576700,
        577990
      ]
    ]
  },
  {
    "verse_key": "56:94",
    "timestamp_from": 578390,
    "timestamp_to": 582130,
    "duration": 3740,
    "segments": [
      [
        1,
        578690,
        580290
      ],
      [
        2,
        580290,
        582130
      ]
    ]
  },
  {
    "verse_key": "56:95",
    "timestamp_from": 582550,
    "timestamp_to": 589800,
    "duration": 7250,
    "segments": [
      [
        1,
        582750,
        584590
      ],
      [
        2,
        584590,
        585710
      ],
      [
        3,
        585710,
        586010
      ],
      [
        4,
        586090,
        587160
      ],
      [
        5,
        587220,
        589800
      ]
    ]
  },
  {
    "verse_key": "56:96",
    "timestamp_from": 590220,
    "timestamp_to": 597810,
    "duration": 7590,
    "segments": [
      [
        1,
        590520,
        592000
      ],
      [
        2,
        592000,
        592860
      ],
      [
        3,
        592860,
        593860
      ],
      [
        4,
        594100,
        597810
      ]
    ]
  }
]