[
  {
    "verse_key": "80:1",
    "timestamp_from": 100,
    "timestamp_to": 4830,
    "duration": 4730,
    "segments": [
      [
        1,
        0,
        3130
      ],
      [
        2,
        3130,
        4830
      ]
    ]
  },
  {
    "verse_key": "80:2",
    "timestamp_from": 4970,
    "timestamp_to": 8810,
    "duration": 3840,
    "segments": [
      [
        1,
        4970,
        6070
      ],
      [
        2,
        6110,
        7860
      ],
      [
        3,
        7860,
        8810
      ]
    ]
  },
  {
    "verse_key": "80:3",
    "timestamp_from": 8990,
    "timestamp_to": 13190,
    "duration": 4200,
    "segments": [
      [
        1,
        9190,
        9790
      ],
      [
        2,
        9790,
        10470
      ],
      [
        3,
        10470,
        11820
      ],
      [
        4,
        11820,
        13190
      ]
    ]
  },
  {
    "verse_key": "80:4",
    "timestamp_from": 13380,
    "timestamp_to": 17740,
    "duration": 4360,
    "segments": [
      [
        1,
        13380,
        13800
      ],
      [
        2,
        13800,
        14860
      ],
      [
        3,
        14860,
        16860
      ],
      [
        4,
        16860,
        17740
      ]
    ]
  },
  {
    "verse_key": "80:5",
    "timestamp_from": 17960,
    "timestamp_to": 20610,
    "duration": 2650,
    "segments": [
      [
        1,
        18160,
        19550
      ],
      [
        2,
        19550,
        19800
      ],
      [
        3,
        19880,
        20610
      ]
    ]
  },
  {
    "verse_key": "80:6",
    "timestamp_from": 20720,
    "timestamp_to": 23850,
    "duration": 3130,
    "segments": [
      [
        1,
        20720,
        22280
      ],
      [
        2,
        22280,
        22820
      ],
      [
        3,
        22820,
        23850
      ]
    ]
  },
  {
    "verse_key": "80:7",
    "timestamp_from": 24110,
    "timestamp_to": 27410,
    "duration": 3300,
    "segments": [
      [
        1,
        24310,
        24870
      ],
      [
        2,
        24870,
        25510
      ],
      [
        3,
        25550,
        26300
      ],
      [
        4,
        26300,
        27410
      ]
    ]
  },
  {
    "verse_key": "80:8",
    "timestamp_from": 27550,
    "timestamp_to": 32630,
    "duration": 5080,
    "segments": [
      [
        1,
        27750,
        29080
      ],
      [
        2,
        29080,
        30030
      ],
      [
        3,
        30030,
        31940
      ],
      [
        4,
        32000,
        32630
      ]
    ]
  },
  {
    "verse_key": "80:9",
    "timestamp_from": 32700,
    "timestamp_to": 34240,
    "duration": 1540,
    "segments": [
      [
        1,
        32700,
        33240
      ],
      [
        2,
        33240,
        34240
      ]
    ]
  },
  {
    "verse_key": "80:10",
    "timestamp_from": 34480,
    "timestamp_to": 37740,
    "duration": 3260,
    "segments": [
      [
        1,
        34480,
        36180
      ],
      [
        2,
        36180,
        36860
      ],
      [
        3,
        36860,
        37740
      ]
    ]
  },
  {
    "verse_key": "80:11",
    "timestamp_from": 38040,
    "timestamp_to": 41870,
    "duration": 3830,
    "segments": [
      [
        1,
        38240,
        39170
      ],
      [
        2,
        39170,
        40940
      ],
      [
        3,
        40940,
        41870
      ]
    ]
  },
  {
    "verse_key": "80:12",
    "timestamp_from": 42150,
    "timestamp_to": 46240,
    "duration": 4090,
    "segments": [
      [
        1,
        42150,
        43330
      ],
      [
        2,
        43450,
        45340
      ],
      [
        3,
        45340,
        46240
      ]
    ]
  },
  {
    "verse_key": "80:13",
    "timestamp_from": 46370,
    "timestamp_to": 49640,
    "duration": 3270,
    "segments": [
      [
        1,
        46370,
        46790
      ],
      [
        2,
        46790,
        48450
      ],
      [
        3,
        48450,
        49640
      ]
    ]
  },
  {
    "verse_key": "80:14",
    "timestamp_from": 49940,
    "timestamp_to": 53030,
    "duration": 3090,
    "segments": [
      [
        1,
        49940,
        51770
      ],
      [
        2,
        51770,
        53030
      ]
    ]
  },
  {
    "verse_key": "80:15",
    "timestamp_from": 53180,
    "timestamp_to": 55000,
    "duration": 1820,
    "segments": [
      [
        1,
        53180,
        54210
      ],
      [
        2,
        54210,
        55000
      ]
    ]
  },
  {
    "verse_key": "80:16",
    "timestamp_from": 55280,
    "timestamp_to": 58560,
    "duration": 3280,
    "segments": [
      [
        1,
        55280,
        56120
      ],
      [
        2,
        57530,
        58560
      ]
    ]
  },
  {
    "verse_key": "80:17",
    "timestamp_from": 58710,
    "timestamp_to": 63970,
    "duration": 5260,
    "segments": [
      [
        1,
        58710,
        59370
      ],
      [
        2,
        59370,
        61160
      ],
      [
        3,
        61160,
        62800
      ],
      [
        4,
        62800,
        63970
      ]
    ]
  },
  {
    "verse_key": "80:18",
    "timestamp_from": 64110,
    "timestamp_to": 66520,
    "duration": 2410,
    "segments": [
      [
        1,
        64110,
        64470
      ],
      [
        2,
        64470,
        65010
      ],
      [
        3,
        65010,
        65720
      ],
      [
        4,
        65720,
        66520
      ]
    ]
  },
  {
    "verse_key": "80:19",
    "timestamp_from": 66820,
    "timestamp_to": 70950,
    "duration": 4130,
    "segments": [
      [
        1,
        66820,
        67730
      ],
      [
        2,
        67730,
        68680
      ],
      [
        3,
        68680,
        69670
      ],
      [
        4,
        69670,
        70900
      ]
    ]
  },
  {
    "verse_key": "80:20",
    "timestamp_from": 71080,
    "timestamp_to": 74340,
    "duration": 3260,
    "segments": [
      [
        1,
        71080,
        72400
      ],
      [
        2,
        72400,
        73270
      ],
      [
        3,
        73270,
        74340
      ]
    ]
  },
  {
    "verse_key": "80:21",
    "timestamp_from": 74460,
    "timestamp_to": 78460,
    "duration": 4000,
    "segments": [
      [
        1,
        74460,
        75830
      ],
      [
        2,
        75830,
        77120
      ],
      [
        3,
        77120,
        78460
      ]
    ]
  },
  {
    "verse_key": "80:22",
    "timestamp_from": 78590,
    "timestamp_to": 83890,
    "duration": 5300,
    "segments": [
      [
        1,
        78590,
        79620
      ],
      [
        2,
        79620,
        80170
      ],
      [
        3,
        80210,
        82030
      ],
      [
        4,
        82030,
        83840
      ]
    ]
  },
  {
    "verse_key": "80:23",
    "timestamp_from": 84020,
    "timestamp_to": 89330,
    "duration": 5310,
    "segments": [
      [
        1,
        84020,
        84830
      ],
      [
        2,
        84830,
        86080
      ],
      [
        3,
        86080,
        86650
      ],
      [
        4,
        86650,
        88410
      ],
      [
        5,
        88410,
        89330
      ]
    ]
  },
  {
    "verse_key": "80:24",
    "timestamp_from": 89480,
    "timestamp_to": 93760,
    "duration": 4280,
    "segments": [
      [
        1,
        89480,
        90820
      ],
      [
        2,
        90840,
        92200
      ],
      [
        3,
        92200,
        92700
      ],
      [
        4,
        92700,
        93760
      ]
    ]
  },
  {
    "verse_key": "80:25",
    "timestamp_from": 93890,
    "timestamp_to": 98640,
    "duration": 4750,
    "segments": [
      [
        1,
        93890,
        95390
      ],
      [
        2,
        95390,
        96090
      ],
      [
        3,
        96090,
        97800
      ],
      [
        4,
        97800,
        98640
      ]
    ]
  },
  {
    "verse_key": "80:26",
    "timestamp_from": 98750,
    "timestamp_to": 102560,
    "duration": 3810,
    "segments": [
      [
        1,
        98750,
        100100
      ],
      [
        2,
        100100,
        100870
      ],
      [
        3,
        100870,
        101610
      ],
      [
        4,
        101610,
        102560
      ]
    ]
  },
  {
    "verse_key": "80:27",
    "timestamp_from": 102700,
    "timestamp_to": 105980,
    "duration": 3280,
    "segments": [
      [
        1,
        102700,
        104440
      ],
      [
        2,
        104440,
        105160
      ],
      [
        3,
        105160,
        105980
      ]
    ]
  },
  {
    "verse_key": "80:28",
    "timestamp_from": 106120,
    "timestamp_to": 108700,
    "duration": 2580,
    "segments": [
      [
        1,
        106320,
        107700
      ],
      [
        2,
        107700,
        108700
      ]
    ]
  },
  {
    "verse_key": "80:29",
    "timestamp_from": 108900,
    "timestamp_to": 112170,
    "duration": 3270,
    "segments": [
      [
        1,
        109100,
        110980
      ],
      [
        2,
        110980,
        112170
      ]
    ]
  },
  {
    "verse_key": "80:30",
    "timestamp_from": 112330,
    "timestamp_to": 115510,
    "duration": 3180,
    "segments": [
      [
        1,
        112330,
        114540
      ],
      [
        2,
        114540,
        115510
      ]
    ]
  },
  {
    "verse_key": "80:31",
    "timestamp_from": 115610,
    "timestamp_to": 118850,
    "duration": 3240,
    "segments": [
      [
        1,
        115810,
        117900
      ],
      [
        2,
        117900,
        118850
      ]
    ]
  },
  {
    "verse_key": "80:32",
    "timestamp_from": 119000,
    "timestamp_to": 122420,
    "duration": 3420,
    "segments": [
      [
        1,
        119200,
        120080
      ],
      [
        2,
        120080,
        120670
      ],
      [
        3,
        120670,
        122420
      ]
    ]
  },
  {
    "verse_key": "80:33",
    "timestamp_from": 122620,
    "timestamp_to": 129360,
    "duration": 6740,
    "segments": [
      [
        1,
        122820,
        123690
      ],
      [
        2,
        123690,
        125860
      ],
      [
        3,
        125860,
        129360
      ]
    ]
  },
  {
    "verse_key": "80:34",
    "timestamp_from": 129510,
    "timestamp_to": 134560,
    "duration": 5050,
    "segments": [
      [
        1,
        129510,
        130140
      ],
      [
        2,
        130140,
        130850
      ],
      [
        3,
        130850,
        131450
      ],
      [
        4,
        131570,
        131900
      ],
      [
        5,
        131900,
        134510
      ]
    ]
  },
  {
    "verse_key": "80:35",
    "timestamp_from": 134570,
    "timestamp_to": 137790,
    "duration": 3220,
    "segments": [
      [
        1,
        134570,
        136020
      ],
      [
        2,
        136020,
        137790
      ]
    ]
  },
  {
    "verse_key": "80:36",
    "timestamp_from": 137820,
    "timestamp_to": 140930,
    "duration": 3110,
    "segments": [
      [
        1,
        137820,
        139450
      ],
      [
        2,
        139450,
        140930
      ]
    ]
  },
  {
    "verse_key": "80:37",
    "timestamp_from": 140960,
    "timestamp_to": 147880,
    "duration": 6920,
    "segments": [
      [
        1,
        140960,
        141680
      ],
      [
        2,
        141680,
        141900
      ],
      [
        3,
        141960,
        143500
      ],
      [
        4,
        143500,
        145000
      ],
      [
        5,
        145060,
        146220
      ],
      [
        6,
        146220,
        147880
      ]
    ]
  },
  {
    "verse_key": "80:38",
    "timestamp_from": 147930,
    "timestamp_to": 151610,
    "duration": 3680,
    "segments": [
      [
        1,
        147930,
        148810
      ],
      [
        2,
        149170,
        150210
      ],
      [
        3,
        150590,
        151610
      ]
    ]
  },
  {
    "verse_key": "80:39",
    "timestamp_from": 151630,
    "timestamp_to": 154760,
    "duration": 3130,
    "segments": [
      [
        1,
        151830,
        153460
      ],
      [
        2,
        153460,
        154760
      ]
    ]
  },
  {
    "verse_key": "80:40",
    "timestamp_from": 155020,
    "timestamp_to": 159320,
    "duration": 4300,
    "segments": [
      [
        1,
        155020,
        156080
      ],
      [
        2,
        156080,
        157600
      ],
      [
        3,
        157600,
        158470
      ],
      [
        4,
        158470,
        159320
      ]
    ]
  },
  {
    "verse_key": "80:41",
    "timestamp_from": 159360,
    "timestamp_to": 161710,
    "duration": 2350,
    "segments": [
      [
        1,
        159560,
        160710
      ],
      [
        2,
        160710,
        161710
      ]
    ]
  },
  {
    "verse_key": "80:42",
    "timestamp_from": 161760,
    "timestamp_to": 167190,
    "duration": 5430,
    "segments": [
      [
        1,
        161760,
        164270
      ],
      [
        2,
        164350,
        164770
      ],
      [
        3,
        164770,
        165730
      ],
      [
        4,
        165730,
        167190
      ]
    ]
  }
]