[
  {
    "verse_key": "35:1",
    "timestamp_from": 100,
    "timestamp_to": 29350,
    "duration": 29250,
    "segments": [
      [
        1,
        0,
        6460
      ],
      [
        2,
        6460,
        7130
      ],
      [
        3,
        7130,
        7770
      ],
      [
        4,
        7770,
        8890
      ],
      [
        5,
        8890,
        9640
      ],
      [
        6,
        9640,
        10190
      ],
      [
        7,
        10230,
        11990
      ],
      [
        8,
        11990,
        12620
      ],
      [
        9,
        12620,
        13510
      ],
      [
        10,
        13510,
        14310
      ],
      [
        11,
        14700,
        15370
      ],
      [
        12,
        15370,
        16230
      ],
      [
        13,
        16230,
        18090
      ],
      [
        14,
        18090,
        18760
      ],
      [
        15,
        18760,
        18980
      ],
      [
        16,
        18980,
        19500
      ],
      [
        17,
        19600,
        19840
      ],
      [
        18,
        19920,
        23260
      ],
      [
        19,
        23260,
        24470
      ],
      [
        20,
        24490,
        25110
      ],
      [
        21,
        25110,
        25630
      ],
      [
        22,
        25630,
        26190
      ],
      [
        23,
        26190,
        27330
      ],
      [
        24,
        27330,
        29350
      ]
    ]
  },
  {
    "verse_key": "35:2",
    "timestamp_from": 29510,
    "timestamp_to": 43060,
    "duration": 13550,
    "segments": [
      [
        1,
        29510,
        29880
      ],
      [
        2,
        29880,
        30620
      ],
      [
        3,
        30620,
        31160
      ],
      [
        4,
        31160,
        32130
      ],
      [
        5,
        32210,
        32450
      ],
      [
        6,
        32450,
        33560
      ],
      [
        7,
        33560,
        34130
      ],
      [
        8,
        34130,
        34800
      ],
      [
        9,
        34820,
        35900
      ],
      [
        10,
        35900,
        36470
      ],
      [
        11,
        36470,
        37290
      ],
      [
        12,
        37290,
        37610
      ],
      [
        13,
        37610,
        38270
      ],
      [
        14,
        38270,
        38800
      ],
      [
        15,
        38800,
        39550
      ],
      [
        16,
        39550,
        40320
      ],
      [
        17,
        40520,
        41190
      ],
      [
        18,
        41190,
        42120
      ],
      [
        19,
        42120,
        43060
      ]
    ]
  },
  {
    "verse_key": "35:3",
    "timestamp_from": 43710,
    "timestamp_to": 68290,
    "duration": 24580,
    "segments": [
      [
        1,
        44010,
        44310
      ],
      [
        2,
        45870,
        46650
      ],
      [
        3,
        46850,
        47600
      ],
      [
        4,
        47600,
        48120
      ],
      [
        5,
        48120,
        48820
      ],
      [
        6,
        48820,
        49430
      ],
      [
        7,
        49430,
        50280
      ],
      [
        8,
        50280,
        51110
      ],
      [
        9,
        51110,
        51450
      ],
      [
        10,
        51450,
        52310
      ],
      [
        11,
        52390,
        52910
      ],
      [
        12,
        53010,
        53760
      ],
      [
        13,
        53760,
        54970
      ],
      [
        14,
        54970,
        55360
      ],
      [
        15,
        55360,
        58110
      ],
      [
        16,
        58110,
        59460
      ],
      [
        17,
        59460,
        61850
      ],
      [
        18,
        61850,
        63070
      ],
      [
        19,
        63070,
        63480
      ],
      [
        20,
        63480,
        63960
      ],
      [
        21,
        63960,
        66200
      ]
    ]
  },
  {
    "verse_key": "35:4",
    "timestamp_from": 68730,
    "timestamp_to": 79530,
    "duration": 10800,
    "segments": [
      [
        1,
        68930,
        69820
      ],
      [
        2,
        69820,
        70950
      ],
      [
        3,
        71030,
        71590
      ],
      [
        4,
        71590,
        72435
      ],
      [
        5,
        72435,
        72900
      ],
      [
        6,
        72940,
        74590
      ],
      [
        7,
        74590,
        75380
      ],
      [
        8,
        75520,
        76160
      ],
      [
        9,
        76220,
        76860
      ],
      [
        10,
        76860,
        77600
      ],
      [
        11,
        77600,
        79480
      ]
    ]
  },
  {
    "verse_key": "35:5",
    "timestamp_from": 79640,
    "timestamp_to": 98030,
    "duration": 18390,
    "segments": [
      [
        1,
        79640,
        79840
      ],
      [
        2,
        81260,
        82150
      ],
      [
        3,
        82770,
        83510
      ],
      [
        4,
        83510,
        84790
      ],
      [
        5,
        84790,
        85390
      ],
      [
        6,
        85390,
        86040
      ],
      [
        7,
        86040,
        87080
      ],
      [
        8,
        87080,
        87610
      ],
      [
        9,
        87610,
        89600
      ],
      [
        10,
        89600,
        90570
      ],
      [
        11,
        90570,
        91860
      ],
      [
        12,
        91860,
        92420
      ],
      [
        13,
        92420,
        95440
      ],
      [
        14,
        95440,
        96430
      ]
    ]
  },
  {
    "verse_key": "35:6",
    "timestamp_from": 98140,
    "timestamp_to": 111840,
    "duration": 13700,
    "segments": [
      [
        1,
        98140,
        99050
      ],
      [
        2,
        99050,
        99940
      ],
      [
        3,
        99960,
        100530
      ],
      [
        4,
        100530,
        101750
      ],
      [
        5,
        101750,
        102950
      ],
      [
        6,
        102950,
        104300
      ],
      [
        7,
        104300,
        106040
      ],
      [
        8,
        106040,
        106680
      ],
      [
        9,
        106680,
        107560
      ],
      [
        10,
        107560,
        108470
      ],
      [
        11,
        108550,
        108860
      ],
      [
        12,
        108860,
        109770
      ],
      [
        13,
        109770,
        111840
      ]
    ]
  },
  {
    "verse_key": "35:7",
    "timestamp_from": 111900,
    "timestamp_to": 126870,
    "duration": 14970,
    "segments": [
      [
        1,
        112100,
        112910
      ],
      [
        2,
        112910,
        113730
      ],
      [
        3,
        113730,
        114300
      ],
      [
        4,
        114300,
        115680
      ],
      [
        5,
        115680,
        117500
      ],
      [
        6,
        117680,
        118640
      ],
      [
        7,
        118720,
        119480
      ],
      [
        8,
        119480,
        120310
      ],
      [
        9,
        120310,
        121710
      ],
      [
        10,
        121710,
        122790
      ],
      [
        11,
        122790,
        124020
      ],
      [
        12,
        124020,
        125170
      ],
      [
        13,
        125170,
        126870
      ]
    ]
  },
  {
    "verse_key": "35:8",
    "timestamp_from": 127010,
    "timestamp_to": 155360,
    "duration": 28350,
    "segments": [
      [
        1,
        127010,
        128510
      ],
      [
        2,
        128510,
        129220
      ],
      [
        3,
        129220,
        129770
      ],
      [
        4,
        129790,
        131300
      ],
      [
        5,
        131300,
        132220
      ],
      [
        6,
        132220,
        133110
      ],
      [
        7,
        133110,
        134300
      ],
      [
        8,
        134420,
        135560
      ],
      [
        9,
        135560,
        136290
      ],
      [
        10,
        136290,
        137030
      ],
      [
        11,
        137030,
        137600
      ],
      [
        12,
        137600,
        139720
      ],
      [
        13,
        139820,
        140770
      ],
      [
        14,
        140770,
        141370
      ],
      [
        15,
        141370,
        143590
      ],
      [
        16,
        143590,
        144160
      ],
      [
        17,
        144160,
        144930
      ],
      [
        18,
        144930,
        145530
      ],
      [
        19,
        145610,
        146480
      ],
      [
        20,
        146480,
        148920
      ],
      [
        21,
        148920,
        150900
      ],
      [
        22,
        150960,
        151750
      ],
      [
        23,
        151750,
        153240
      ],
      [
        24,
        153240,
        153830
      ],
      [
        25,
        153830,
        155360
      ]
    ]
  },
  {
    "verse_key": "35:9",
    "timestamp_from": 156600,
    "timestamp_to": 179060,
    "duration": 22460,
    "segments": [
      [
        1,
        157100,
        157980
      ],
      [
        2,
        158000,
        159140
      ],
      [
        3,
        159140,
        159870
      ],
      [
        4,
        159870,
        160510
      ],
      [
        5,
        160610,
        161490
      ],
      [
        6,
        161490,
        166620
      ],
      [
        7,
        166620,
        167690
      ],
      [
        8,
        167690,
        168160
      ],
      [
        9,
        168160,
        168790
      ],
      [
        10,
        169560,
        170860
      ],
      [
        11,
        170860,
        172020
      ],
      [
        12,
        172020,
        172460
      ],
      [
        13,
        172460,
        173070
      ],
      [
        14,
        173070,
        173570
      ],
      [
        15,
        173570,
        175100
      ],
      [
        16,
        175100,
        176060
      ],
      [
        17,
        177040,
        179060
      ]
    ]
  },
  {
    "verse_key": "35:10",
    "timestamp_from": 179170,
    "timestamp_to": 204840,
    "duration": 25670,
    "segments": [
      [
        1,
        179170,
        180440
      ],
      [
        2,
        180440,
        181090
      ],
      [
        3,
        181110,
        181770
      ],
      [
        4,
        181770,
        182690
      ],
      [
        5,
        182690,
        183760
      ],
      [
        6,
        183760,
        184670
      ],
      [
        7,
        184670,
        186170
      ],
      [
        8,
        186170,
        187230
      ],
      [
        9,
        187230,
        187810
      ],
      [
        10,
        187810,
        188580
      ],
      [
        11,
        188620,
        189250
      ],
      [
        12,
        189250,
        190280
      ],
      [
        13,
        190280,
        191160
      ],
      [
        14,
        191160,
        192340
      ],
      [
        15,
        192340,
        193420
      ],
      [
        16,
        193420,
        194390
      ],
      [
        17,
        194390,
        195610
      ],
      [
        18,
        195610,
        196090
      ],
      [
        19,
        196090,
        197400
      ],
      [
        20,
        197400,
        199210
      ],
      [
        21,
        199470,
        200300
      ],
      [
        22,
        200300,
        202650
      ],
      [
        23,
        202750,
        203200
      ],
      [
        24,
        203200,
        204840
      ]
    ]
  },
  {
    "verse_key": "35:11",
    "timestamp_from": 204910,
    "timestamp_to": 242620,
    "duration": 37710,
    "segments": [
      [
        1,
        204910,
        205840
      ],
      [
        2,
        205840,
        207010
      ],
      [
        3,
        207530,
        207620
      ],
      [
        4,
        207620,
        208930
      ],
      [
        5,
        208930,
        212180
      ],
      [
        6,
        212180,
        212970
      ],
      [
        7,
        212970,
        214300
      ],
      [
        8,
        214300,
        215840
      ],
      [
        9,
        215840,
        216740
      ],
      [
        10,
        216740,
        218520
      ],
      [
        11,
        218520,
        219200
      ],
      [
        12,
        219200,
        219910
      ],
      [
        13,
        220010,
        220350
      ],
      [
        14,
        220350,
        221570
      ],
      [
        15,
        221570,
        222120
      ],
      [
        16,
        222120,
        222740
      ],
      [
        17,
        222740,
        223460
      ],
      [
        18,
        223460,
        224410
      ],
      [
        19,
        224610,
        225370
      ],
      [
        20,
        225370,
        226710
      ],
      [
        21,
        226830,
        226930
      ],
      [
        22,
        227740,
        229250
      ],
      [
        23,
        229250,
        229780
      ],
      [
        24,
        229780,
        230830
      ],
      [
        25,
        230830,
        231140
      ],
      [
        26,
        231140,
        232430
      ],
      [
        27,
        232430,
        234330
      ],
      [
        28,
        234330,
        234680
      ],
      [
        29,
        234680,
        236910
      ],
      [
        30,
        237050,
        238670
      ],
      [
        31,
        238670,
        239430
      ],
      [
        32,
        239510,
        239890
      ],
      [
        33,
        239890,
        240530
      ],
      [
        34,
        240630,
        242620
      ]
    ]
  },
  {
    "verse_key": "35:12",
    "timestamp_from": 242730,
    "timestamp_to": 282790,
    "duration": 40060,
    "segments": [
      [
        1,
        242730,
        243360
      ],
      [
        2,
        243360,
        244210
      ],
      [
        3,
        244210,
        245430
      ],
      [
        4,
        245430,
        245800
      ],
      [
        5,
        245800,
        250910
      ],
      [
        6,
        250910,
        251800
      ],
      [
        7,
        251820,
        254680
      ],
      [
        8,
        254800,
        256140
      ],
      [
        9,
        256140,
        256790
      ],
      [
        10,
        256790,
        257870
      ],
      [
        11,
        257870,
        259980
      ],
      [
        12,
        259980,
        260990
      ],
      [
        13,
        260990,
        262400
      ],
      [
        14,
        262400,
        263500
      ],
      [
        15,
        263500,
        264360
      ],
      [
        16,
        264360,
        265170
      ],
      [
        17,
        265330,
        269530
      ],
      [
        18,
        269530,
        271500
      ],
      [
        19,
        271500,
        273620
      ],
      [
        20,
        273620,
        274100
      ],
      [
        21,
        274220,
        274880
      ],
      [
        22,
        275000,
        275600
      ],
      [
        23,
        275600,
        276540
      ],
      [
        24,
        276540,
        277590
      ],
      [
        25,
        277690,
        278540
      ],
      [
        26,
        278540,
        279580
      ],
      [
        27,
        279580,
        281260
      ],
      [
        28,
        281260,
        282790
      ]
    ]
  },
  {
    "verse_key": "35:13",
    "timestamp_from": 284860,
    "timestamp_to": 312200,
    "duration": 27340,
    "segments": [
      [
        1,
        285360,
        285980
      ],
      [
        2,
        286140,
        286750
      ],
      [
        3,
        286750,
        287080
      ],
      [
        4,
        287540,
        288370
      ],
      [
        5,
        288370,
        289160
      ],
      [
        6,
        289660,
        290500
      ],
      [
        7,
        290500,
        290600
      ],
      [
        8,
        290820,
        291350
      ],
      [
        9,
        291350,
        292220
      ],
      [
        10,
        292220,
        292890
      ],
      [
        11,
        292890,
        294100
      ],
      [
        12,
        294100,
        295360
      ],
      [
        13,
        295360,
        296130
      ],
      [
        14,
        296130,
        297560
      ],
      [
        15,
        297560,
        299510
      ],
      [
        16,
        299510,
        300390
      ],
      [
        17,
        300590,
        301290
      ],
      [
        18,
        301290,
        302190
      ],
      [
        19,
        302190,
        302690
      ],
      [
        20,
        302690,
        303880
      ],
      [
        21,
        303880,
        304870
      ],
      [
        22,
        304870,
        305900
      ],
      [
        23,
        305900,
        306960
      ],
      [
        24,
        306960,
        307600
      ],
      [
        25,
        307820,
        308210
      ],
      [
        26,
        308210,
        309290
      ],
      [
        27,
        309290,
        310090
      ],
      [
        28,
        310090,
        312200
      ]
    ]
  },
  {
    "verse_key": "35:14",
    "timestamp_from": 312360,
    "timestamp_to": 330540,
    "duration": 18180,
    "segments": [
      [
        1,
        312360,
        313320
      ],
      [
        2,
        313320,
        314130
      ],
      [
        3,
        314170,
        314620
      ],
      [
        4,
        314620,
        315490
      ],
      [
        5,
        315490,
        317350
      ],
      [
        6,
        317390,
        317710
      ],
      [
        7,
        317810,
        318520
      ],
      [
        8,
        318520,
        318710
      ],
      [
        9,
        318710,
        319720
      ],
      [
        10,
        319720,
        320830
      ],
      [
        11,
        320830,
        321680
      ],
      [
        12,
        321680,
        322840
      ],
      [
        13,
        322840,
        324060
      ],
      [
        14,
        324060,
        325670
      ],
      [
        15,
        325670,
        326250
      ],
      [
        16,
        326250,
        327320
      ],
      [
        17,
        327400,
        327960
      ],
      [
        18,
        327960,
        330540
      ]
    ]
  },
  {
    "verse_key": "35:15",
    "timestamp_from": 330740,
    "timestamp_to": 344910,
    "duration": 14170,
    "segments": [
      [
        1,
        330740,
        332520
      ],
      [
        2,
        332520,
        333300
      ],
      [
        3,
        333970,
        334620
      ],
      [
        4,
        334620,
        335600
      ],
      [
        5,
        335600,
        338240
      ],
      [
        6,
        338240,
        338630
      ],
      [
        7,
        338710,
        340730
      ],
      [
        8,
        340730,
        341860
      ],
      [
        9,
        341860,
        342290
      ],
      [
        10,
        342290,
        342870
      ]
    ]
  },
  {
    "verse_key": "35:16",
    "timestamp_from": 344980,
    "timestamp_to": 351910,
    "duration": 6930,
    "segments": [
      [
        1,
        344980,
        346230
      ],
      [
        2,
        346230,
        346780
      ],
      [
        3,
        346820,
        348040
      ],
      [
        4,
        348040,
        348750
      ],
      [
        5,
        348750,
        349600
      ],
      [
        6,
        349840,
        351910
      ]
    ]
  },
  {
    "verse_key": "35:17",
    "timestamp_from": 351960,
    "timestamp_to": 357560,
    "duration": 5600,
    "segments": [
      [
        1,
        351960,
        353010
      ],
      [
        2,
        353250,
        354110
      ],
      [
        3,
        354190,
        354650
      ],
      [
        4,
        354710,
        355440
      ],
      [
        5,
        355440,
        357560
      ]
    ]
  },
  {
    "verse_key": "35:18",
    "timestamp_from": 357590,
    "timestamp_to": 395530,
    "duration": 37940,
    "segments": [
      [
        1,
        357590,
        358190
      ],
      [
        2,
        358190,
        358490
      ],
      [
        3,
        358710,
        359770
      ],
      [
        4,
        360330,
        360900
      ],
      [
        5,
        360900,
        362050
      ],
      [
        6,
        362050,
        362920
      ],
      [
        7,
        362920,
        363480
      ],
      [
        8,
        363480,
        364560
      ],
      [
        9,
        364560,
        364820
      ],
      [
        10,
        365060,
        366000
      ],
      [
        11,
        366000,
        366390
      ],
      [
        12,
        366390,
        369930
      ],
      [
        13,
        369930,
        371270
      ],
      [
        14,
        371270,
        372640
      ],
      [
        15,
        372640,
        373190
      ],
      [
        16,
        373190,
        373650
      ],
      [
        17,
        373730,
        374100
      ],
      [
        18,
        374100,
        375010
      ],
      [
        19,
        375430,
        376640
      ],
      [
        20,
        376640,
        377910
      ],
      [
        21,
        377950,
        378800
      ],
      [
        22,
        378800,
        379660
      ],
      [
        23,
        379660,
        380770
      ],
      [
        24,
        380770,
        381710
      ],
      [
        25,
        381710,
        382600
      ],
      [
        26,
        382600,
        384630
      ],
      [
        27,
        384630,
        385870
      ],
      [
        28,
        385870,
        386930
      ],
      [
        29,
        386930,
        388870
      ],
      [
        30,
        388870,
        390080
      ],
      [
        31,
        390080,
        391420
      ],
      [
        32,
        391420,
        392110
      ],
      [
        33,
        392190,
        393010
      ],
      [
        34,
        393110,
        395530
      ]
    ]
  },
  {
    "verse_key": "35:19",
    "timestamp_from": 395850,
    "timestamp_to": 400230,
    "duration": 4380,
    "segments": [
      [
        1,
        396050,
        396650
      ],
      [
        2,
        396650,
        397370
      ],
      [
        3,
        397390,
        398060
      ],
      [
        4,
        398060,
        400230
      ]
    ]
  },
  {
    "verse_key": "35:20",
    "timestamp_from": 400430,
    "timestamp_to": 404650,
    "duration": 4220,
    "segments": [
      [
        1,
        400430,
        400920
      ],
      [
        2,
        400920,
        402030
      ],
      [
        3,
        402030,
        402680
      ],
      [
        4,
        403080,
        404650
      ]
    ]
  },
  {
    "verse_key": "35:21",
    "timestamp_from": 404740,
    "timestamp_to": 408050,
    "duration": 3310,
    "segments": [
      [
        1,
        404740,
        405140
      ],
      [
        2,
        405140,
        405810
      ],
      [
        3,
        405810,
        406180
      ],
      [
        4,
        406180,
        408050
      ]
    ]
  },
  {
    "verse_key": "35:22",
    "timestamp_from": 408120,
    "timestamp_to": 429010,
    "duration": 20890,
    "segments": [
      [
        1,
        408120,
        408720
      ],
      [
        2,
        408720,
        409460
      ],
      [
        3,
        409460,
        412120
      ],
      [
        4,
        412120,
        412490
      ],
      [
        5,
        412490,
        414880
      ],
      [
        6,
        414880,
        416350
      ],
      [
        7,
        416410,
        417120
      ],
      [
        8,
        417120,
        417880
      ],
      [
        9,
        417880,
        418730
      ],
      [
        10,
        418730,
        419230
      ],
      [
        11,
        421660,
        423210
      ],
      [
        12,
        423210,
        424450
      ],
      [
        13,
        424450,
        425240
      ],
      [
        14,
        425940,
        426820
      ],
      [
        15,
        426820,
        427050
      ],
      [
        16,
        427050,
        429010
      ]
    ]
  },
  {
    "verse_key": "35:23",
    "timestamp_from": 429060,
    "timestamp_to": 432860,
    "duration": 3800,
    "segments": [
      [
        1,
        429060,
        429420
      ],
      [
        2,
        429420,
        430530
      ],
      [
        3,
        430610,
        431050
      ],
      [
        4,
        431050,
        432860
      ]
    ]
  },
  {
    "verse_key": "35:24",
    "timestamp_from": 432870,
    "timestamp_to": 446590,
    "duration": 13720,
    "segments": [
      [
        1,
        432870,
        434470
      ],
      [
        2,
        434470,
        435710
      ],
      [
        3,
        435770,
        436550
      ],
      [
        4,
        436630,
        437790
      ],
      [
        5,
        437790,
        439280
      ],
      [
        6,
        439280,
        439640
      ],
      [
        7,
        440440,
        440790
      ],
      [
        8,
        440790,
        442730
      ],
      [
        9,
        442730,
        443440
      ],
      [
        10,
        443440,
        443950
      ],
      [
        11,
        443950,
        444710
      ],
      [
        12,
        444710,
        446590
      ]
    ]
  },
  {
    "verse_key": "35:25",
    "timestamp_from": 446740,
    "timestamp_to": 466350,
    "duration": 19610,
    "segments": [
      [
        1,
        446740,
        447460
      ],
      [
        2,
        447460,
        448600
      ],
      [
        3,
        448640,
        449205
      ],
      [
        4,
        449205,
        449970
      ],
      [
        5,
        449970,
        450750
      ],
      [
        6,
        450750,
        451330
      ],
      [
        7,
        451330,
        452210
      ],
      [
        8,
        452210,
        453980
      ],
      [
        9,
        453980,
        455490
      ],
      [
        10,
        455490,
        460470
      ],
      [
        11,
        460470,
        461900
      ],
      [
        12,
        461900,
        464420
      ],
      [
        13,
        464420,
        466300
      ]
    ]
  },
  {
    "verse_key": "35:26",
    "timestamp_from": 466400,
    "timestamp_to": 474550,
    "duration": 8150,
    "segments": [
      [
        1,
        466400,
        467570
      ],
      [
        2,
        467570,
        468460
      ],
      [
        3,
        468460,
        469010
      ],
      [
        4,
        469010,
        469930
      ],
      [
        5,
        469930,
        470920
      ],
      [
        6,
        470920,
        471660
      ],
      [
        7,
        471660,
        474550
      ]
    ]
  },
  {
    "verse_key": "35:27",
    "timestamp_from": 474830,
    "timestamp_to": 503460,
    "duration": 28630,
    "segments": [
      [
        1,
        474830,
        475350
      ],
      [
        2,
        475350,
        475630
      ],
      [
        3,
        475690,
        475930
      ],
      [
        4,
        476170,
        476930
      ],
      [
        5,
        476930,
        478250
      ],
      [
        6,
        478250,
        478560
      ],
      [
        7,
        478560,
        479140
      ],
      [
        8,
        480000,
        481700
      ],
      [
        9,
        481700,
        482850
      ],
      [
        10,
        482850,
        483380
      ],
      [
        11,
        483380,
        484610
      ],
      [
        12,
        484610,
        486210
      ],
      [
        12,
        486210,
        487855
      ],
      [
        13,
        487855,
        488820
      ],
      [
        14,
        488820,
        490560
      ],
      [
        15,
        490560,
        491150
      ],
      [
        16,
        491150,
        492010
      ],
      [
        17,
        492010,
        493210
      ],
      [
        18,
        493210,
        494130
      ],
      [
        19,
        494130,
        495280
      ],
      [
        20,
        495280,
        496300
      ],
      [
        21,
        496300,
        500300
      ],
      [
        22,
        500300,
        501560
      ],
      [
        22,
        501560,
        503460
      ]
    ]
  },
  {
    "verse_key": "35:28",
    "timestamp_from": 503580,
    "timestamp_to": 526780,
    "duration": 23200,
    "segments": [
      [
        1,
        503480,
        504080
      ],
      [
        2,
        504860,
        505510
      ],
      [
        3,
        505510,
        508230
      ],
      [
        4,
        508230,
        509330
      ],
      [
        5,
        509330,
        510360
      ],
      [
        6,
        510360,
        511560
      ],
      [
        7,
        511560,
        513020
      ],
      [
        8,
        513020,
        515330
      ],
      [
        9,
        515330,
        515950
      ],
      [
        10,
        515970,
        516740
      ],
      [
        11,
        516740,
        517090
      ],
      [
        12,
        517090,
        518200
      ],
      [
        13,
        518200,
        521810
      ],
      [
        14,
        521810,
        523260
      ],
      [
        15,
        523300,
        523990
      ],
      [
        16,
        523990,
        524920
      ],
      [
        17,
        524920,
        526780
      ]
    ]
  },
  {
    "verse_key": "35:29",
    "timestamp_from": 526910,
    "timestamp_to": 547480,
    "duration": 20570,
    "segments": [
      [
        1,
        526910,
        527890
      ],
      [
        2,
        527950,
        528650
      ],
      [
        3,
        528650,
        529520
      ],
      [
        4,
        529520,
        530350
      ],
      [
        5,
        530370,
        530980
      ],
      [
        6,
        530980,
        531810
      ],
      [
        7,
        531810,
        532580
      ],
      [
        8,
        532580,
        533780
      ],
      [
        9,
        533780,
        534420
      ],
      [
        10,
        534420,
        538930
      ],
      [
        11,
        538930,
        540660
      ],
      [
        12,
        540800,
        542580
      ],
      [
        13,
        542600,
        543630
      ],
      [
        14,
        543630,
        544700
      ],
      [
        15,
        544780,
        545700
      ],
      [
        16,
        545700,
        547430
      ]
    ]
  },
  {
    "verse_key": "35:30",
    "timestamp_from": 547510,
    "timestamp_to": 560050,
    "duration": 12540,
    "segments": [
      [
        1,
        547510,
        548800
      ],
      [
        2,
        548800,
        550010
      ],
      [
        3,
        550010,
        550990
      ],
      [
        4,
        552270,
        552450
      ],
      [
        5,
        552450,
        553490
      ],
      [
        6,
        553510,
        555530
      ],
      [
        7,
        555530,
        557090
      ],
      [
        8,
        557090,
        560000
      ]
    ]
  },
  {
    "verse_key": "35:31",
    "timestamp_from": 560080,
    "timestamp_to": 574860,
    "duration": 14780,
    "segments": [
      [
        1,
        560080,
        561320
      ],
      [
        2,
        561320,
        562780
      ],
      [
        3,
        562780,
        563360
      ],
      [
        4,
        563380,
        563710
      ],
      [
        5,
        563710,
        564570
      ],
      [
        6,
        564570,
        564870
      ],
      [
        7,
        564870,
        565470
      ],
      [
        8,
        565470,
        566270
      ],
      [
        9,
        566330,
        566940
      ],
      [
        10,
        566940,
        567400
      ],
      [
        11,
        567400,
        569150
      ],
      [
        12,
        569150,
        570050
      ],
      [
        13,
        570090,
        570700
      ],
      [
        14,
        570700,
        571650
      ],
      [
        15,
        571830,
        573090
      ],
      [
        16,
        573090,
        574810
      ]
    ]
  },
  {
    "verse_key": "35:32",
    "timestamp_from": 574980,
    "timestamp_to": 600390,
    "duration": 25410,
    "segments": [
      [
        1,
        574980,
        576200
      ],
      [
        2,
        576200,
        577020
      ],
      [
        3,
        577020,
        577920
      ],
      [
        4,
        577920,
        578720
      ],
      [
        5,
        578760,
        579670
      ],
      [
        6,
        579670,
        579960
      ],
      [
        7,
        579960,
        581540
      ],
      [
        8,
        581540,
        582380
      ],
      [
        9,
        582380,
        583280
      ],
      [
        10,
        583280,
        584240
      ],
      [
        11,
        584240,
        585560
      ],
      [
        12,
        585560,
        587080
      ],
      [
        13,
        587080,
        587880
      ],
      [
        14,
        587880,
        589030
      ],
      [
        15,
        589030,
        591340
      ],
      [
        16,
        591340,
        591980
      ],
      [
        17,
        591980,
        596480
      ],
      [
        18,
        596480,
        597220
      ],
      [
        19,
        597280,
        597700
      ],
      [
        20,
        597700,
        598390
      ],
      [
        21,
        598390,
        600340
      ]
    ]
  },
  {
    "verse_key": "35:33",
    "timestamp_from": 600480,
    "timestamp_to": 620000,
    "duration": 19520,
    "segments": [
      [
        1,
        600480,
        601760
      ],
      [
        2,
        601760,
        602760
      ],
      [
        3,
        602760,
        604200
      ],
      [
        4,
        604200,
        605220
      ],
      [
        5,
        605220,
        605920
      ],
      [
        6,
        605920,
        606180
      ],
      [
        7,
        606180,
        607150
      ],
      [
        8,
        607150,
        607830
      ],
      [
        9,
        607830,
        614410
      ],
      [
        10,
        614410,
        615940
      ],
      [
        11,
        615940,
        617260
      ],
      [
        12,
        617260,
        618040
      ],
      [
        13,
        618040,
        620000
      ]
    ]
  },
  {
    "verse_key": "35:34",
    "timestamp_from": 620120,
    "timestamp_to": 631590,
    "duration": 11470,
    "segments": [
      [
        1,
        620020,
        620790
      ],
      [
        2,
        620790,
        621390
      ],
      [
        3,
        621390,
        621760
      ],
      [
        4,
        621780,
        623330
      ],
      [
        5,
        623330,
        624030
      ],
      [
        6,
        624030,
        624960
      ],
      [
        7,
        624960,
        626130
      ],
      [
        8,
        626130,
        627660
      ],
      [
        9,
        627660,
        628500
      ],
      [
        10,
        628500,
        629810
      ],
      [
        11,
        629810,
        631590
      ]
    ]
  },
  {
    "verse_key": "35:35",
    "timestamp_from": 631710,
    "timestamp_to": 644420,
    "duration": 12710,
    "segments": [
      [
        1,
        631710,
        632960
      ],
      [
        2,
        632960,
        633860
      ],
      [
        3,
        633860,
        634400
      ],
      [
        4,
        634420,
        635340
      ],
      [
        5,
        636060,
        636140
      ],
      [
        6,
        636140,
        637120
      ],
      [
        7,
        637180,
        637640
      ],
      [
        8,
        637640,
        638650
      ],
      [
        9,
        638650,
        639400
      ],
      [
        10,
        639400,
        640370
      ],
      [
        11,
        640370,
        640940
      ],
      [
        12,
        640940,
        641930
      ],
      [
        13,
        641930,
        642670
      ],
      [
        14,
        642670,
        644420
      ]
    ]
  },
  {
    "verse_key": "35:36",
    "timestamp_from": 644510,
    "timestamp_to": 664900,
    "duration": 20390,
    "segments": [
      [
        1,
        644510,
        645650
      ],
      [
        2,
        645650,
        646440
      ],
      [
        3,
        646440,
        647010
      ],
      [
        4,
        647010,
        647590
      ],
      [
        5,
        647590,
        648980
      ],
      [
        6,
        648980,
        649330
      ],
      [
        7,
        649330,
        650100
      ],
      [
        8,
        650100,
        651050
      ],
      [
        9,
        651050,
        652950
      ],
      [
        6,
        652950,
        653390
      ],
      [
        7,
        653390,
        654220
      ],
      [
        8,
        654220,
        655180
      ],
      [
        9,
        655180,
        655500
      ],
      [
        10,
        655700,
        656340
      ],
      [
        11,
        656340,
        656910
      ],
      [
        12,
        656910,
        657900
      ],
      [
        13,
        657900,
        658870
      ],
      [
        14,
        658870,
        659200
      ],
      [
        15,
        659200,
        660890
      ],
      [
        16,
        660890,
        661740
      ],
      [
        17,
        661810,
        662590
      ],
      [
        18,
        662590,
        663010
      ],
      [
        18,
        663110,
        664900
      ]
    ]
  },
  {
    "verse_key": "35:37",
    "timestamp_from": 665050,
    "timestamp_to": 699170,
    "duration": 34120,
    "segments": [
      [
        1,
        665050,
        665620
      ],
      [
        2,
        665620,
        666930
      ],
      [
        3,
        666930,
        667650
      ],
      [
        4,
        667650,
        669210
      ],
      [
        5,
        669210,
        670200
      ],
      [
        6,
        670200,
        670790
      ],
      [
        7,
        670790,
        673550
      ],
      [
        8,
        673550,
        674610
      ],
      [
        6,
        674610,
        675260
      ],
      [
        7,
        675280,
        676210
      ],
      [
        8,
        676210,
        676660
      ],
      [
        9,
        676660,
        677070
      ],
      [
        10,
        677070,
        678610
      ],
      [
        11,
        678610,
        679200
      ],
      [
        12,
        679200,
        680600
      ],
      [
        13,
        680600,
        682590
      ],
      [
        14,
        682690,
        683180
      ],
      [
        15,
        683180,
        684300
      ],
      [
        16,
        684300,
        684860
      ],
      [
        17,
        684860,
        685870
      ],
      [
        18,
        685870,
        687510
      ],
      [
        19,
        687510,
        691480
      ],
      [
        20,
        691540,
        693700
      ],
      [
        21,
        693700,
        694820
      ],
      [
        22,
        694820,
        695280
      ],
      [
        23,
        695400,
        696730
      ],
      [
        24,
        696730,
        697410
      ],
      [
        25,
        697410,
        699170
      ]
    ]
  },
  {
    "verse_key": "35:38",
    "timestamp_from": 699260,
    "timestamp_to": 710740,
    "duration": 11480,
    "segments": [
      [
        1,
        699260,
        700120
      ],
      [
        2,
        700200,
        700900
      ],
      [
        3,
        700900,
        701570
      ],
      [
        4,
        701570,
        702090
      ],
      [
        5,
        702090,
        703260
      ],
      [
        6,
        703260,
        704400
      ],
      [
        7,
        704400,
        706290
      ],
      [
        8,
        706290,
        707560
      ],
      [
        9,
        707560,
        708560
      ],
      [
        10,
        708560,
        710740
      ]
    ]
  },
  {
    "verse_key": "35:39",
    "timestamp_from": 711140,
    "timestamp_to": 731740,
    "duration": 20600,
    "segments": [
      [
        1,
        711340,
        711740
      ],
      [
        2,
        711760,
        712360
      ],
      [
        3,
        712360,
        713300
      ],
      [
        4,
        713300,
        715610
      ],
      [
        5,
        715610,
        715840
      ],
      [
        6,
        715840,
        716420
      ],
      [
        7,
        716420,
        717130
      ],
      [
        8,
        717130,
        717900
      ],
      [
        9,
        717900,
        718580
      ],
      [
        10,
        718580,
        719540
      ],
      [
        11,
        719600,
        720130
      ],
      [
        12,
        720130,
        720840
      ],
      [
        13,
        720840,
        722030
      ],
      [
        14,
        722030,
        722880
      ],
      [
        15,
        722880,
        723760
      ],
      [
        16,
        723760,
        724590
      ],
      [
        17,
        724590,
        725250
      ],
      [
        18,
        725250,
        726550
      ],
      [
        19,
        726550,
        727120
      ],
      [
        20,
        727120,
        727810
      ],
      [
        21,
        727810,
        729030
      ],
      [
        22,
        729030,
        729890
      ],
      [
        23,
        729890,
        730590
      ],
      [
        24,
        730590,
        731740
      ]
    ]
  },
  {
    "verse_key": "35:40",
    "timestamp_from": 731940,
    "timestamp_to": 765360,
    "duration": 33420,
    "segments": [
      [
        1,
        732140,
        732520
      ],
      [
        2,
        732520,
        733560
      ],
      [
        3,
        733560,
        736300
      ],
      [
        4,
        736300,
        737060
      ],
      [
        5,
        737060,
        737910
      ],
      [
        6,
        737910,
        738410
      ],
      [
        7,
        738410,
        740370
      ],
      [
        8,
        740370,
        741780
      ],
      [
        9,
        741780,
        743080
      ],
      [
        10,
        743080,
        743770
      ],
      [
        11,
        743770,
        744500
      ],
      [
        12,
        744500,
        744970
      ],
      [
        13,
        744970,
        745460
      ],
      [
        14,
        745460,
        745670
      ],
      [
        15,
        745750,
        746310
      ],
      [
        16,
        746310,
        747530
      ],
      [
        17,
        747530,
        747750
      ],
      [
        18,
        747750,
        748990
      ],
      [
        19,
        748990,
        749290
      ],
      [
        20,
        749290,
        750660
      ],
      [
        21,
        750660,
        752200
      ],
      [
        20,
        752200,
        752540
      ],
      [
        21,
        752540,
        753860
      ],
      [
        22,
        753860,
        755400
      ],
      [
        23,
        755400,
        755940
      ],
      [
        24,
        755940,
        756480
      ],
      [
        25,
        756480,
        758050
      ],
      [
        26,
        758050,
        758870
      ],
      [
        27,
        758870,
        759230
      ],
      [
        28,
        759230,
        759780
      ],
      [
        29,
        759780,
        760420
      ],
      [
        30,
        760420,
        761530
      ],
      [
        31,
        761530,
        762610
      ],
      [
        32,
        762610,
        763300
      ],
      [
        33,
        763300,
        763940
      ],
      [
        33,
        763940,
        765360
      ]
    ]
  },
  {
    "verse_key": "35:41",
    "timestamp_from": 765410,
    "timestamp_to": 783640,
    "duration": 18230,
    "segments": [
      [
        1,
        765410,
        766510
      ],
      [
        2,
        766570,
        767220
      ],
      [
        3,
        767220,
        767930
      ],
      [
        4,
        767930,
        769150
      ],
      [
        5,
        769150,
        769990
      ],
      [
        6,
        769990,
        770900
      ],
      [
        7,
        770900,
        772350
      ],
      [
        8,
        772350,
        773320
      ],
      [
        9,
        773380,
        774980
      ],
      [
        10,
        774980,
        775290
      ],
      [
        11,
        775290,
        776690
      ],
      [
        12,
        776690,
        777020
      ],
      [
        13,
        777020,
        777520
      ],
      [
        14,
        778370,
        779140
      ],
      [
        15,
        779140,
        779830
      ],
      [
        16,
        779850,
        781520
      ],
      [
        17,
        781520,
        782040
      ],
      [
        18,
        782040,
        782840
      ],
      [
        19,
        782840,
        783640
      ]
    ]
  },
  {
    "verse_key": "35:42",
    "timestamp_from": 783750,
    "timestamp_to": 807100,
    "duration": 23350,
    "segments": [
      [
        1,
        783750,
        785120
      ],
      [
        2,
        785120,
        785890
      ],
      [
        3,
        785890,
        786290
      ],
      [
        4,
        786610,
        787440
      ],
      [
        5,
        787440,
        788330
      ],
      [
        6,
        788330,
        794990
      ],
      [
        7,
        794990,
        795680
      ],
      [
        8,
        795740,
        797170
      ],
      [
        9,
        797190,
        797940
      ],
      [
        10,
        797940,
        798230
      ],
      [
        11,
        798230,
        798780
      ],
      [
        12,
        798780,
        799150
      ],
      [
        13,
        799850,
        800970
      ],
      [
        14,
        800970,
        803030
      ],
      [
        15,
        803030,
        804120
      ],
      [
        16,
        804120,
        804470
      ],
      [
        17,
        804470,
        805340
      ],
      [
        18,
        805340,
        806020
      ],
      [
        19,
        806020,
        807100
      ]
    ]
  },
  {
    "verse_key": "35:43",
    "timestamp_from": 807340,
    "timestamp_to": 833320,
    "duration": 25980,
    "segments": [
      [
        1,
        807340,
        808900
      ],
      [
        2,
        808940,
        809310
      ],
      [
        3,
        809310,
        809800
      ],
      [
        4,
        809800,
        810480
      ],
      [
        5,
        810480,
        811600
      ],
      [
        6,
        811600,
        812160
      ],
      [
        7,
        812160,
        813020
      ],
      [
        8,
        813020,
        813680
      ],
      [
        9,
        813680,
        814450
      ],
      [
        10,
        814450,
        815080
      ],
      [
        11,
        815080,
        816140
      ],
      [
        12,
        816140,
        816660
      ],
      [
        13,
        816660,
        818330
      ],
      [
        14,
        818330,
        818930
      ],
      [
        15,
        818930,
        819870
      ],
      [
        16,
        819870,
        822470
      ],
      [
        17,
        822470,
        823710
      ],
      [
        18,
        823710,
        824340
      ],
      [
        19,
        824340,
        825830
      ],
      [
        20,
        825850,
        826500
      ],
      [
        21,
        826500,
        827660
      ],
      [
        22,
        828020,
        829080
      ],
      [
        23,
        829080,
        829710
      ],
      [
        24,
        829710,
        831100
      ],
      [
        25,
        831120,
        831850
      ],
      [
        26,
        831850,
        833320
      ]
    ]
  },
  {
    "verse_key": "35:44",
    "timestamp_from": 834120,
    "timestamp_to": 858050,
    "duration": 23930,
    "segments": [
      [
        1,
        834420,
        835110
      ],
      [
        2,
        835110,
        835940
      ],
      [
        3,
        835940,
        836250
      ],
      [
        4,
        836250,
        836750
      ],
      [
        5,
        836750,
        838030
      ],
      [
        6,
        838030,
        838610
      ],
      [
        7,
        838610,
        839010
      ],
      [
        8,
        839110,
        839840
      ],
      [
        9,
        839840,
        840770
      ],
      [
        10,
        840770,
        841260
      ],
      [
        11,
        841260,
        842020
      ],
      [
        12,
        842020,
        843060
      ],
      [
        13,
        843060,
        843650
      ],
      [
        14,
        843730,
        844370
      ],
      [
        15,
        844370,
        845490
      ],
      [
        16,
        845490,
        846100
      ],
      [
        17,
        846100,
        846740
      ],
      [
        18,
        846780,
        847440
      ],
      [
        19,
        847440,
        848200
      ],
      [
        20,
        848280,
        849340
      ],
      [
        21,
        849340,
        850560
      ],
      [
        22,
        850560,
        850780
      ],
      [
        23,
        850780,
        852030
      ],
      [
        24,
        852030,
        852500
      ],
      [
        25,
        852500,
        852790
      ],
      [
        26,
        852790,
        853700
      ],
      [
        27,
        853700,
        854820
      ],
      [
        28,
        854820,
        855410
      ],
      [
        29,
        855410,
        857070
      ],
      [
        30,
        857070,
        858050
      ]
    ]
  },
  {
    "verse_key": "35:45",
    "timestamp_from": 858350,
    "timestamp_to": 890300,
    "duration": 31950,
    "segments": [
      [
        1,
        858550,
        859100
      ],
      [
        2,
        859100,
        860110
      ],
      [
        3,
        860130,
        860490
      ],
      [
        4,
        861070,
        861760
      ],
      [
        5,
        861760,
        862270
      ],
      [
        6,
        862270,
        862980
      ],
      [
        7,
        862980,
        863310
      ],
      [
        8,
        863310,
        863860
      ],
      [
        9,
        863860,
        864340
      ],
      [
        10,
        864340,
        868530
      ],
      [
        11,
        868530,
        871640
      ],
      [
        12,
        871640,
        873660
      ],
      [
        13,
        873660,
        877260
      ],
      [
        14,
        877260,
        878430
      ],
      [
        15,
        878430,
        879560
      ],
      [
        16,
        879560,
        880630
      ],
      [
        17,
        880630,
        882460
      ],
      [
        18,
        882460,
        883250
      ],
      [
        19,
        883250,
        884530
      ],
      [
        20,
        884530,
        885460
      ],
      [
        21,
        885460,
        886500
      ],
      [
        22,
        886560,
        887230
      ],
      [
        23,
        887230,
        887830
      ],
      [
        24,
        887830,
        889320
      ],
      [
        25,
        889320,
        890300
      ]
    ]
  }
]